uncch_core/__init__.py
uncch_core/funcs.py
uncch_core/interface.py
uncch_core/pipeline.py
pynipt_plugin_uncch_core-0.0.1.dist-info/METADATA
pynipt_plugin_uncch_core-0.0.1.dist-info/WHEEL
pynipt_plugin_uncch_core-0.0.1.dist-info/top_level.txt
pynipt_plugin_uncch_core-0.0.1.dist-info/RECORD
