Metadata-Version: 2.1
Name: pynipt-plugin-uncch-core
Version: 0.0.1
Summary: UNCCH core module for rsfMRI analysis - pynipt plugin
Home-page: https://github.com/dvm-shlee/pynipt-plugin
Author: SungHo Lee
Author-email: shlee@unc.edu
License: GNLv3
Keywords: pynipt,plugin,pipeline,uncch_core,windows10,windows
Platform: UNKNOWN
Classifier: Development Status :: 4 - Beta
Classifier: License :: OSI Approved :: GNU General Public License v3 (GPLv3)
Classifier: Natural Language :: English
Classifier: Operating System :: POSIX :: Linux
Classifier: Operating System :: MacOS
Classifier: Operating System :: Microsoft :: Windows :: Windows 10
Classifier: Programming Language :: Python :: 3.7
Classifier: Topic :: Software Development
Requires-Python: >3.5, <3.8
Requires-Dist: pynipt (>=0.2.2)
Requires-Dist: nibabel
Requires-Dist: simpleITK
Requires-Dist: rbm (>=0.0.2a0)
Requires-Dist: shleeh (>=0.0.7)
Requires-Dist: slfmri (>=0.0.6)
